traductorsqb/__init__.py
traductorsqb/__main__.py
traductorsqb/matematicas/__init__.py
traductorsqb/matematicas/basico.py
traductorsqb-0.0.5.dist-info/entry_points.txt
traductorsqb-0.0.5.dist-info/WHEEL
traductorsqb-0.0.5.dist-info/METADATA
traductorsqb-0.0.5.dist-info/RECORD
