Metadata-Version: 2.1
Name: traductorsqb
Version: 0.0.5
Summary: Traductor de palabras
Home-page: https://github.com/PythonBasico-AA2021/traductorqcb
License: MIT
Keywords: traductor
Author: Santiago Quiñones
Author-email: lsquinones@gmail.com
Requires-Python: >=3.8,<4.0
Classifier: License :: OSI Approved :: MIT License
Classifier: Programming Language :: Python :: 3
Classifier: Programming Language :: Python :: 3.8
Requires-Dist: click (>=8.0.1,<9.0.0)
Requires-Dist: translate (==3.4.0)
Project-URL: Repository, https://github.com/PythonBasico-AA2021/traductorqcb
